[
  {
    "sourceId": 111144,
    "code": "00000G2FFJMT475JWJG075X3964U03FH",
    "url": "https://legislatie.just.ro/Public/FormaPrintabila/00000G2FFJMT475JWJG075X3964U03FH",
    "fetchedAt": "2025-04-15T18:37:58.479Z",
    "chunkIndex": 0,
    "type": "text",
    "text": "HOTĂRÂRE nr. 969 din 26 august 2009\nEMITENT\nGUVERNUL\nMONITORUL OFICIAL nr. 617 din 14 septembrie 2009\nÎn temeiul art. 108 din Constituția României, republicată,\nGuvernul României adoptă prezenta hotărâre.\nArticolul I\nHotărârea Guvernului nr. 769/2004 privind organizarea și funcționarea Reprezentanței Naționale de Legătură la Comandamentul Aliat pentru Transformare, publicată în Monitorul Oficial al României, Partea I, nr. 469 din 25 mai 2004, se modifică după cum urmează:1. La articolul 4, alineatul (1) va avea următorul cuprins:Articolul 4(1) Șeful Reprezentanței are funcția prevăzută în statul de organizare cu gradul de colonel și este reprezentantul militar al șefului Statului Major General la ACT. ... 2. Anexa nr. 1 se modifică și se înlocuiește cu anexa care face parte integrantă din prezenta hotărâre. ...\nHotărârea Guvernului nr. 769/2004 privind organizarea și funcționarea Reprezentanței Naționale de Legătură la Comandamentul Aliat pentru Transformare, publicată în Monitorul Oficial al României, Partea I, nr. 469 din 25 mai 2004, se modifică după cum urmează:\nArticolul 4"
  },
  {
    "sourceId": 111144,
    "code": "00000G2FFJMT475JWJG075X3964U03FH",
    "url": "https://legislatie.just.ro/Public/FormaPrintabila/00000G2FFJMT475JWJG075X3964U03FH",
    "fetchedAt": "2025-04-15T18:37:58.479Z",
    "chunkIndex": 1,
    "type": "text",
    "text": "(1) Șeful Reprezentanței are funcția prevăzută în statul de organizare cu gradul de colonel și este reprezentantul militar al șefului Statului Major General la ACT.\nArticolul II\nAnexa*) la prezenta hotărâre se comunică instituțiilor interesate de către Ministerul Apărării Naționale.\n\t\t\t\t\t\tNotă ...\n\t\t\t*) Anexa nu se publică, fiind clasificată potrivit legii\nAnexa*) la prezenta hotărâre se comunică instituțiilor interesate de către Ministerul Apărării Naționale.\nArticolul III\nPrezenta hotărâre intră în vigoare la data de 1 octombrie 2009, cu excepția prevederilor din anexă referitoare la gradul și echivalarea funcției de locțiitor al reprezentantului militar al șefului Statului Major General la Comandamentul Aliat pentru Transformare, care rămân în vigoare până la data de 25 iunie 2010.\nPrezenta hotărâre intră în vigoare la data de 1 octombrie 2009, cu excepția prevederilor din anexă referitoare la gradul și echivalarea funcției de locțiitor al reprezentantului militar al șefului Statului Major General la Comandamentul Aliat pentru Transformare, care rămân în vigoare până la data de 25 iunie 2010.\nBucurești, 26 august 2009.\nNr. 969.\n___________"
  }
]