{
  "question": "Care sunt drepturile juridice ale unui angajat aflat în concediu medical de odihnă sau concediu medical pe bază de certificat medical, conform legislației muncii din România, inclusiv drepturile salariale, protecția față de concediere și obligațiile angajatorului în această perioadă?",
  "relevantChunks": [
    {
      "chunkId": 576937,
      "text": "cu modificările și completările ulterioare, indemnizația aferentă certificatului de concediu medical se plătește de către fiecare angajator. Baza de calcul al indemnizației se constituie cu venitul obținut la fiecare angajator.(9) Pe copiile certificate se va înscrie «Conform cu originalul» și se vor aplica parafa și semnătura medicului curant, precum și, după caz, parafa și semnătura medicului șef de secție, în cazul concediului medical acordat la externare pentru o perioadă mai mare de 7 zile.(10) Persoanele prevăzute la alin. (1)-(3) au obligația respectării prevederilor art. 2. (la 09-03-2023, Articolul 58 din Sectiunea a 7-a , Capitolul II a fost modificat de Punctul 3, Articolul I din ORDINUL nr. 670 din 7 martie 2023, publicat în MONITORUL OFICIAL nr. 199 din 09 martie 2023 )\nArticolul 54 -\nArticolul 54 -\nÎn cazul în care, potrivit legii, angajatorul își suspendă temporar activitatea sau activitatea acestuia încetează prin: divizare ori fuziune, dizolvare, reorganizare, lichidare, reorganizare judiciară, lichidare judiciară, faliment sau prin orice altă modalitate prevăzută de lege, drepturile prevăzute la art. 2 alin. (1) din Ordonanța de urgență a Guvernului nr. 158/2005, aprobată cu modificări și completări prin Legea nr. 399/2006, cu modificările și completările ulterioare, care sau născut anterior ivirii acestor situații, se achită din bugetul Fondului național unic de asigurări sociale de sănătate de către casele de asigurări de sănătate unde medicul de familie al asiguratului are încheiată convenție. Pentru aceste situații, indemnizațiile de asigurări sociale de sănătate la care au dreptul asigurații prevăzuți la art. 1 alin. (1) lit. A și B din Ordonanța de urgență a Guvernului nr. 158/2005, aprobată cu modificări și completări prin Legea nr. 399/2006, cu modificările și completările ulterioare, sunt achitate în condițiile menținerii concediului medical pentru aceeași afecțiune.\nÎn cazul în care, potrivit legii, angajatorul își suspendă temporar activitatea sau activitatea acestuia încetează prin: divizare ori fuziune, dizolvare, reorganizare, lichidare, reorganizare judiciară, lichidare judiciară, faliment sau prin orice altă modalitate prevăzută de lege, drepturile prevăzute la art. 2 alin. (1) din Ordonanța de urgență a Guvernului nr. 158/2005, aprobată cu modificări și completări prin Legea nr. 399/2006, cu modificările și completările ulterioare, care sau născut anterior ivirii acestor situații, se achită din bugetul Fondului național unic de asigurări sociale de sănătate de către casele de asigurări de sănătate unde medicul de familie al asiguratului are încheiată convenție. Pentru aceste situații, indemnizațiile de asigurări sociale de sănătate la care au dreptul asigurații prevăzuți la art. 1 alin. (1) lit. A și B din Ordonanța de urgență a Guvernului nr. 158/2005, aprobată cu modificări și completări prin Legea nr. 399/2006, cu modificările și completările ulterioare, sunt achitate în condițiile menținerii concediului medical pentru aceeași afecțiune.\nArticolul 55 -\nArticolul 55 -\nDrepturile achitate în condițiile prevăzute la art. 54, care sunt suportate de angajator potrivit art. 12 lit. A din Ordonanța de urgență a Guvernului nr. 158/2005, aprobată cu modificări și completări prin Legea nr. 399/2006, cu modificările și completările ulterioare, se recuperează de către casele de asigurări de sănătate de la angajator, conform legii.\nDrepturile achitate în condițiile prevăzute la art. 54, care sunt suportate de angajator potrivit art. 12 lit. A din Ordonanța de urgență a Guvernului nr. 158/2005, aprobată cu modificări și completări prin Legea nr. 399/2006, cu modificările și completările ulterioare, se recuperează de către casele de asigurări de sănătate de la angajator, conform legii.\nArticolul 56 -",
      "sourceId": "282138",
      "chunkIndex": 165,
      "title": "NORME din 5 ianuarie 2018"
    },
    {
      "chunkId": 1938217,
      "text": "art. 2 alin. (4) la casele de asigurări de sănătate, în condițiile în care se solicită restituirea sumelor reprezentând indemnizații plătite angajaților proprii care au beneficiat de certificate de concediu medical.(10) Formularele originale ale certificatelor de concediu medical, respectiv exemplarele 1 (alb) și 2 (roz), se depun de către persoana asigurată la plătitorii de indemnizații de asigurări sociale de sănătate prevăzuți la art. 36 alin. (3) din Ordonanța de urgență a Guvernului nr. 158/2005, aprobată cu modificări și completări prin Legea nr. 399/2006, cu modificările și completările ulterioare, în termen de 60 de zile calendaristice de la data eliberării acestora.(11) Certificatele de concediu medical, care cuprind a 91-a zi sau depășesc 183 de zile, cele acordate pentru risc\nmaternal, precum și cele acordate de medici, alții decât medicii de familie, care au fost eliberate până la data instituirii stării de urgență prevăzută de Decretul nr. 195/2020 privind instituirea stării de urgență pe teritoriul României, se plătesc fără avizul medicului expert al asigurărilor sociale, fără avizul medicului de medicina muncii, respectiv fără avizul medicului de familie.(12) Prevederile alin. (4), (9) și (10) sunt aplicabile și certificatelor de concediu medical prevăzute la alin. (11).(13) La externarea din spital a pacientului cu COVID-19, medicul curant eliberează certificatul de concediu medical atât pentru perioada internării, cât și pentru durata externării cu înscrierea codului de indemnizație corespunzător.(14) Pentru situațiile prevăzute la alin. (13), în cazul în care la externarea din spital se impune continuarea îngrijirii pacientului, medicul curant stabilește perioada necesară îngrijirii și eliberează un nou certificat de concediu medical pentru perioada acordată la externare.(15) Pentru situațiile prevăzute la alin. (14), dacă după expirarea concediului medical acordat la ieșirea din spital starea sănătății pacientului nu permite reluarea activității, medicul de familie, pe baza scrisorii medicale eliberate de medicul curant din spital, poate prelungi concediul medical pentru aceeași afecțiune cu cel mult 14 zile. ... 14. Anexa nr. 7 se modifică și se înlocuiește cu anexa care face parte integrantă din prezentul ordin. ...",
      "sourceId": "224445",
      "chunkIndex": 5,
      "title": "ORDIN nr. 502/417/2020"
    }
  ]
}